CL22006UNO/GaussianElimination.py
CL22006UNO/_init_.py
cl22006uno-1.0.2.dist-info/METADATA
cl22006uno-1.0.2.dist-info/WHEEL
cl22006uno-1.0.2.dist-info/entry_points.txt
cl22006uno-1.0.2.dist-info/top_level.txt
cl22006uno-1.0.2.dist-info/RECORD
